adala-0.0.4.dist-info/METADATA
adala-0.0.4.dist-info/WHEEL
adala-0.0.4.dist-info/licenses/LICENSE
adala/__init__.py
adala/agents/__init__.py
adala/agents/base.py
adala/environments/__init__.py
adala/environments/base.py
adala/environments/code.py
adala/environments/console.py
adala/environments/servers/__init__.py
adala/environments/servers/base.py
adala/environments/servers/discord_bot.py
adala/environments/web.py
adala/memories/__init__.py
adala/memories/base.py
adala/memories/file_memory.py
adala/memories/vectordb.py
adala/runtimes/__init__.py
adala/runtimes/_guidance.py
adala/runtimes/_langchain.py
adala/runtimes/_openai.py
adala/runtimes/base.py
adala/skills/__init__.py
adala/skills/_base.py
adala/skills/collection/__init__.py
adala/skills/collection/classification.py
adala/skills/collection/qa.py
adala/skills/collection/rag.py
adala/skills/collection/summarization.py
adala/skills/collection/text_generation.py
adala/skills/collection/translation.py
adala/skills/skillset.py
adala/utils/__init__.py
adala/utils/internal_data.py
adala/utils/logs.py
adala/utils/matching.py
adala/utils/parse.py
adala-0.0.4.dist-info/RECORD
