Metadata-Version: 2.1
Name: adala
Version: 0.0.4
Summary: Adala: Autonomous Data Labeling Agent
Author-Email: HumanSignal <hello@humansignal.com>
Classifier: Programming Language :: Python :: 3
Classifier: License :: OSI Approved :: Apache Software License
Classifier: Operating System :: OS Independent
Requires-Python: <3.12,>=3.8.8
Requires-Dist: pandas
Requires-Dist: openai==0.28.1
Requires-Dist: guidance==0.0.64
Requires-Dist: pydantic>=2
Requires-Dist: rich>=13
Requires-Dist: redis-om
Requires-Dist: fastapi>=0.104.1
Requires-Dist: aiosqlite>=0.19.0
Requires-Dist: ipython>=8.12.3
Requires-Dist: chromadb>=0.4.18
Requires-Dist: tenacity>=8.2.3
